airstack/__init__.py
airstack/constant.py
airstack/execute_query.py
airstack/generic.py
airstack/send_request.py
test_graphql_sdk-0.1.1.dist-info/METADATA
test_graphql_sdk-0.1.1.dist-info/WHEEL
test_graphql_sdk-0.1.1.dist-info/top_level.txt
test_graphql_sdk-0.1.1.dist-info/RECORD
