Metadata-Version: 2.1
Name: test-graphql-sdk
Version: 0.1.1
Summary: Python sdk for airstack apis
Home-page: https://github.com/Airstack-xyz/airstack-python-sdk
Author: Sarvesh
Author-email: sarveshsingh.03@gmail.com
Project-URL: Bug Tracker, https://github.com/Airstack-xyz/airstack-python-sdk/issues
Classifier: Programming Language :: Python :: 3
Classifier: License :: OSI Approved :: MIT License
Classifier: Operating System :: OS Independent
Requires-Python: >=3.6
Requires-Dist: aiohttp (==3.8.4)
Requires-Dist: graphql-core (==2.3.1)
